easymunk/__init__.py
easymunk/easymunk.py
easymunk-0.0.1.dist-info/METADATA
easymunk-0.0.1.dist-info/RECORD
easymunk-0.0.1.dist-info/WHEEL
easymunk-0.0.1.dist-info/top_level.txt
