Metadata-Version: 2.1
Name: easymunk
Version: 0.0.1
Summary: An easy, versatile interface and processing handler for the munkres module.
Home-page: https://github.com/Andrew-Hogan/easymunk
Author: Andrew M. Hogan
Author-email: drewthedruid@gmail.com
License: UNKNOWN
Platform: any
Classifier: Intended Audience :: Developers
Classifier: Intended Audience :: Science/Research
Classifier: Programming Language :: Python :: 3
Classifier: License :: OSI Approved :: Apache Software License
Classifier: Operating System :: OS Independent
Classifier: Topic :: Software Development :: Libraries :: Python Modules
Classifier: Topic :: Scientific/Engineering :: Mathematics
Classifier: Topic :: Utilities
Requires-Dist: munkres
